data_bridge/__init__.py
data_bridge/cli.py
data_bridge/comm/dataloader.py
data_bridge/comm/dataset.py
data_bridge/formats/__init__.py
data_bridge/formats/base.py
data_bridge/formats/binidx.py
data_bridge/formats/energon.py
data_bridge/formats/jsonl.py
data_bridge/formats/registry.py
data_bridge/formats/webdataset.py
data_bridge/utils/__init__.py
dataloader_bridge-0.1.1.dist-info/LICENSE
dataloader_bridge-0.1.1.dist-info/METADATA
dataloader_bridge-0.1.1.dist-info/WHEEL
dataloader_bridge-0.1.1.dist-info/entry_points.txt
dataloader_bridge-0.1.1.dist-info/top_level.txt
dataloader_bridge-0.1.1.dist-info/RECORD
