Metadata-Version: 2.1
Name: dataloader-bridge
Version: 0.1.1
Summary: A comprehensive dataset conversion toolkit for transforming between different dataset formats
Home-page: https://github.com/yourusername/DataBridge
Author: ziqi-wlb
Author-email: ziqi-wlb <550461236@qq.com>
Maintainer-email: ziqi-wlb <550461236@qq.com>
License: MIT
Project-URL: Homepage, https://github.com/ziqi-wlb/DataBridge
Project-URL: Documentation, https://github.com/ziqi-wlb/DataBridge#readme
Project-URL: Repository, https://github.com/ziqi-wlb/DataBridge
Project-URL: Bug Tracker, https://github.com/ziqi-wlb/DataBridge/issues
Keywords: dataset,conversion,jsonl,webdataset,megatron,energon,nlp,machine-learning
Classifier: Development Status :: 3 - Alpha
Classifier: Intended Audience :: Developers
Classifier: Intended Audience :: Science/Research
Classifier: License :: OSI Approved :: MIT License
Classifier: Operating System :: OS Independent
Classifier: Programming Language :: Python :: 3
Classifier: Programming Language :: Python :: 3.8
Classifier: Programming Language :: Python :: 3.9
Classifier: Programming Language :: Python :: 3.10
Classifier: Programming Language :: Python :: 3.11
Classifier: Topic :: Scientific/Engineering :: Artificial Intelligence
Classifier: Topic :: Software Development :: Libraries :: Python Modules
Requires-Python: >=3.8
License-File: LICENSE
Requires-Dist: webdataset >=0.2.0
Requires-Dist: transformers >=4.20.0
Requires-Dist: torch >=1.12.0
Requires-Dist: tqdm >=4.64.0
Requires-Dist: numpy >=1.21.0
Requires-Dist: click >=8.0.0
Requires-Dist: rich >=12.0.0
Requires-Dist: megatron-core >=0.10.0
Provides-Extra: dev
Requires-Dist: pytest >=7.0.0 ; extra == 'dev'
Requires-Dist: pytest-cov >=4.0.0 ; extra == 'dev'
Requires-Dist: black >=22.0.0 ; extra == 'dev'
Requires-Dist: isort >=5.10.0 ; extra == 'dev'
Requires-Dist: flake8 >=5.0.0 ; extra == 'dev'
Requires-Dist: mypy >=0.991 ; extra == 'dev'
Provides-Extra: test
Requires-Dist: pytest >=7.0.0 ; extra == 'test'
Requires-Dist: pytest-cov >=4.0.0 ; extra == 'test'
